pathways/STENCIL.TTF
pathways/__init__.py
pathways/main.py
pathways_game-0.1.2.dist-info/licenses/LICENSE
pathways_game-0.1.2.dist-info/METADATA
pathways_game-0.1.2.dist-info/WHEEL
pathways_game-0.1.2.dist-info/top_level.txt
pathways_game-0.1.2.dist-info/RECORD
