Metadata-Version: 2.4
Name: pathways-game
Version: 0.1.2
Summary: A game made with pygame
Author-email: Gavin Gilchrist <gavin.d.gilchrist@gmail.com>
License: MIT
Project-URL: Homepage, https://github.com/gavingilchrist/pathways
Requires-Python: >=3.9
License-File: LICENSE
Requires-Dist: numpy>=2.0
Requires-Dist: pygame>=2.6
Dynamic: license-file
